spl_types/__init__.py
spl_types-1.0.8.dist-info/METADATA
spl_types-1.0.8.dist-info/WHEEL
spl_types-1.0.8.dist-info/RECORD
